MERNcraft/__init__.py
MERNcraft/src/MERNcraft.py
MERNcraft/src/__init__.py
MERNcraft/test/__init__.py
MERNcraft/test/test_MERNcraft.py
MERNcraft-1.0.20.dist-info/LICENSE
MERNcraft-1.0.20.dist-info/METADATA
MERNcraft-1.0.20.dist-info/WHEEL
MERNcraft-1.0.20.dist-info/top_level.txt
MERNcraft-1.0.20.dist-info/RECORD
