Metadata-Version: 2.1
Name: MERNcraft
Version: 1.0.20
Summary: MERNcraft is an automation script designed to kickstart your MERN stack application development. It helps you set up a basic project structure with React for the frontend and Express for the backend.
Home-page: https://github.com/Hardvan/MERNcraft
Author: Hardik Pawar
Author-email: hardikpawarh@gmail.com
License: UNKNOWN
Keywords: automation,mern,project,create-react-app,express,mongodb
Platform: UNKNOWN
Classifier: Programming Language :: Python :: 3
Classifier: License :: OSI Approved :: MIT License
Classifier: Operating System :: OS Independent
Requires-Python: >=3.6
License-File: LICENSE
